luxprint/__init__.py
luxprint/core.py
luxprint-1.0.0.dist-info/licenses/LICENSE
luxprint-1.0.0.dist-info/METADATA
luxprint-1.0.0.dist-info/WHEEL
luxprint-1.0.0.dist-info/top_level.txt
luxprint-1.0.0.dist-info/RECORD
