Metadata-Version: 2.4
Name: luxprint
Version: 1.0.0
Summary: Elegant terminal text updater and animated progress bars
Author: YourName
License: MIT
Keywords: terminal,progress,cli,animation
Requires-Python: >=3.8
License-File: LICENSE
Dynamic: license-file
